{
  "id": "EMSOFT",
  "title": "EMSOFT",
  "description": "International Conference on Embedded Software",
  "category": "MX",
  "rank": "B",
  "dblp": "emsoft",
  "years": [
    2010,
    2011,
    2012,
    2013,
    2014,
    2015,
    2016,
    2017,
    2018,
    2019,
    2020,
    2021,
    2022,
    2023,
    2025
  ],
  "by_year": {
    "2010": {
      "Chinese": 6,
      "Russian": 2,
      "English": 15,
      "Korean": 4,
      "Indian": 2,
      "Vietnamese": 1,
      "German": 1,
      "Persian": 1,
      "French": 1
    },
    "2011": {
      "English": 25,
      "Persian": 2,
      "Korean": 5,
      "Russian": 1,
      "Indian": 4,
      "Chinese": 3,
      "Spanish": 1
    },
    "2012": {
      "English": 19,
      "Russian": 2,
      "Indian": 2,
      "Persian": 1,
      "Chinese": 2,
      "Korean": 1,
      "German": 1
    },
    "2013": {
      "English": 22,
      "Chinese": 1,
      "Vietnamese": 1,
      "German": 1,
      "Russian": 1,
      "Korean": 2,
      "Persian": 1
    },
    "2014": {
      "Russian": 1,
      "Chinese": 3,
      "English": 22,
      "Persian": 1,
      "Vietnamese": 1,
      "Korean": 1,
      "Indian": 1
    },
    "2015": {
      "English": 21,
      "Korean": 2,
      "Chinese": 3,
      "Russian": 1,
      "Spanish": 1
    },
    "2016": {
      "Korean": 4,
      "English": 15,
      "Chinese": 8
    },
    "2017": {
      "Korean": 10,
      "English": 52,
      "French": 1,
      "Chinese": 17,
      "Indian": 4,
      "German": 2,
      "Persian": 1
    },
    "2018": {
      "Indian": 3,
      "English": 9,
      "Korean": 2,
      "Russian": 1,
      "Chinese": 2
    },
    "2019": {
      "English": 48,
      "Indian": 3,
      "German": 1,
      "Korean": 5,
      "Chinese": 18,
      "Persian": 1,
      "Vietnamese": 1,
      "Spanish": 1,
      "Russian": 1
    },
    "2020": {
      "English": 12,
      "Chinese": 4
    },
    "2021": {
      "Chinese": 6,
      "Indian": 1,
      "English": 8
    },
    "2022": {
      "English": 6,
      "Chinese": 3,
      "Korean": 1,
      "Indian": 1
    },
    "2023": {
      "Chinese": 3,
      "English": 4,
      "Korean": 1,
      "Vietnamese": 1
    },
    "2025": {
      "Indian": 1,
      "Chinese": 1,
      "Korean": 2,
      "English": 3
    }
  },
  "total": {
    "Chinese": 80,
    "Russian": 10,
    "English": 281,
    "Korean": 40,
    "Indian": 22,
    "Vietnamese": 5,
    "German": 6,
    "Persian": 8,
    "French": 2,
    "Spanish": 3
  },
  "venues": {
    "2025": {
      "city": "Taipei",
      "country": "Taiwan"
    },
    "2023": {
      "city": "Hamburg",
      "country": "Germany"
    },
    "2022": {
      "city": "Shanghai",
      "country": "China"
    },
    "2021": {
      "city": "Virtual",
      "country": null
    },
    "2020": {
      "city": "Singapore",
      "country": "Singapore"
    },
    "2019": {
      "city": "New York",
      "country": "USA"
    },
    "2018": {
      "city": "Torino",
      "country": "Italy"
    },
    "2017": {
      "city": "Seoul",
      "country": "South Korea"
    },
    "2016": {
      "city": "Pittsburgh",
      "country": "USA"
    },
    "2015": {
      "city": "Amsterdam",
      "country": "The Netherlands"
    },
    "2014": {
      "city": "New Delhi",
      "country": "India"
    },
    "2013": {
      "city": "Montreal",
      "country": "Canada"
    },
    "2012": {
      "city": "Tampere",
      "country": "Finland"
    },
    "2011": {
      "city": "Taipei",
      "country": "Taiwan"
    },
    "2010": {
      "city": "Scottsdale",
      "country": "USA"
    },
    "2009": {
      "city": "Grenoble",
      "country": "France"
    },
    "2008": {
      "city": "Atlanta",
      "country": "USA"
    },
    "2007": {
      "city": "Salzburg",
      "country": "Austria"
    },
    "2006": {
      "city": "Seoul",
      "country": "Korea"
    },
    "2005": {
      "city": "Jersey City",
      "country": "USA"
    },
    "2004": {
      "city": "Pisa",
      "country": "Italy"
    },
    "2003": {
      "city": "Philadelphia",
      "country": "USA"
    },
    "2002": {
      "city": "Grenoble",
      "country": "France"
    },
    "2001": {
      "city": "Tahoe City",
      "country": "USA"
    }
  },
  "rank_history": {
    "2011": "C",
    "2012": "B",
    "2015": "B",
    "2019": "B",
    "2022": "B",
    "2026": "B"
  },
  "accept_rates": [
    {
      "year": 2024,
      "submitted": 129,
      "accepted": 28
    },
    {
      "year": 2023,
      "submitted": 90,
      "accepted": 21
    },
    {
      "year": 2022,
      "submitted": 118,
      "accepted": 30
    },
    {
      "year": 2021,
      "submitted": 111,
      "accepted": 28
    },
    {
      "year": 2020,
      "submitted": 138,
      "accepted": 35
    },
    {
      "year": 2018,
      "submitted": 111,
      "accepted": 27
    },
    {
      "year": 2016,
      "submitted": 97,
      "accepted": 25
    },
    {
      "year": 2015,
      "submitted": 85,
      "accepted": 22
    },
    {
      "year": 2014,
      "submitted": 117,
      "accepted": 29
    },
    {
      "year": 2013,
      "submitted": 97,
      "accepted": 27
    },
    {
      "year": 2012,
      "submitted": 95,
      "accepted": 23
    },
    {
      "year": 2011,
      "submitted": 111,
      "accepted": 27
    },
    {
      "year": 2010,
      "submitted": 89,
      "accepted": 29
    },
    {
      "year": 2009,
      "submitted": 106,
      "accepted": 33
    },
    {
      "year": 2008,
      "submitted": 110,
      "accepted": 28
    },
    {
      "year": 2007,
      "submitted": 131,
      "accepted": 29
    },
    {
      "year": 2006,
      "submitted": 94,
      "accepted": 31
    },
    {
      "year": 2005,
      "submitted": 88,
      "accepted": 25
    },
    {
      "year": 2004,
      "submitted": 87,
      "accepted": 31
    },
    {
      "year": 2003,
      "submitted": 60,
      "accepted": 20
    }
  ]
}