{
  "id": "DCC",
  "title": "DCC",
  "description": "Data Compression Conference",
  "category": "DS",
  "rank": "B",
  "dblp": "dcc",
  "years": [
    2010,
    2011,
    2012,
    2013,
    2014,
    2015,
    2016,
    2017,
    2018,
    2019,
    2020,
    2021,
    2022,
    2023,
    2024,
    2025
  ],
  "by_year": {
    "2010": {
      "Chinese": 30,
      "Spanish": 2,
      "English": 54,
      "Japanese": 3,
      "German": 1,
      "Indian": 1,
      "Turkish": 1,
      "Korean": 4
    },
    "2011": {
      "English": 48,
      "Japanese": 2,
      "German": 3,
      "Chinese": 33,
      "Spanish": 2,
      "Korean": 2
    },
    "2012": {
      "English": 37,
      "Chinese": 24,
      "Russian": 1,
      "Turkish": 1,
      "Japanese": 1,
      "Korean": 1,
      "German": 1
    },
    "2013": {
      "Chinese": 29,
      "English": 69,
      "Persian": 1,
      "German": 3,
      "Japanese": 4,
      "Spanish": 3,
      "Russian": 2,
      "Indian": 2
    },
    "2014": {
      "Vietnamese": 1,
      "Chinese": 25,
      "English": 48,
      "German": 3,
      "Indian": 2,
      "Turkish": 2,
      "Japanese": 2,
      "Spanish": 1,
      "French": 1
    },
    "2015": {
      "Chinese": 28,
      "English": 51,
      "Korean": 2,
      "Russian": 2,
      "Spanish": 1,
      "Turkish": 1,
      "Japanese": 1,
      "German": 1
    },
    "2016": {
      "English": 81,
      "Chinese": 30,
      "Indian": 3,
      "Persian": 1,
      "Vietnamese": 1,
      "Spanish": 1,
      "German": 1,
      "Russian": 1
    },
    "2017": {
      "English": 38,
      "Chinese": 39,
      "Russian": 2,
      "Korean": 2,
      "French": 1,
      "Turkish": 1,
      "Indian": 2,
      "German": 1
    },
    "2018": {
      "Chinese": 28,
      "English": 48,
      "German": 2,
      "Japanese": 1,
      "Persian": 1,
      "Vietnamese": 2,
      "Russian": 1
    },
    "2019": {
      "English": 63,
      "Indian": 2,
      "Chinese": 43,
      "German": 5,
      "Korean": 1,
      "Spanish": 1,
      "Persian": 2,
      "Japanese": 1,
      "Turkish": 2,
      "Russian": 2
    },
    "2020": {
      "English": 44,
      "Chinese": 35,
      "Italian": 1,
      "Korean": 1,
      "Persian": 1,
      "German": 2,
      "Indian": 1,
      "Russian": 2,
      "French": 2,
      "Vietnamese": 1
    },
    "2021": {
      "Chinese": 31,
      "English": 41,
      "Persian": 1,
      "Indian": 3,
      "Vietnamese": 1,
      "Russian": 2,
      "French": 1,
      "German": 2
    },
    "2022": {
      "Chinese": 51,
      "English": 42,
      "Indian": 4,
      "Turkish": 3,
      "Korean": 1,
      "Russian": 2
    },
    "2023": {
      "English": 36,
      "Chinese": 41,
      "Italian": 1,
      "Russian": 2,
      "Korean": 1,
      "Turkish": 1
    },
    "2024": {
      "Chinese": 63,
      "English": 44,
      "Persian": 2,
      "German": 2,
      "Russian": 1,
      "Korean": 2,
      "French": 1
    },
    "2025": {
      "English": 44,
      "Spanish": 1,
      "Chinese": 50,
      "Korean": 1,
      "Japanese": 2,
      "Turkish": 1
    }
  },
  "total": {
    "Chinese": 580,
    "Spanish": 12,
    "English": 788,
    "Japanese": 17,
    "German": 27,
    "Indian": 20,
    "Turkish": 13,
    "Korean": 18,
    "Russian": 20,
    "Persian": 9,
    "Vietnamese": 6,
    "French": 6,
    "Italian": 2
  }
}