{
  "id": "SIGMETRICS",
  "title": "SIGMETRICS",
  "description": "International Conference on Measurement and Modeling of Computer Systems",
  "category": "DS",
  "rank": "B",
  "dblp": "sigmetrics",
  "years": [
    2010,
    2011,
    2012,
    2013,
    2014,
    2015,
    2016,
    2017,
    2018,
    2019,
    2020,
    2021,
    2022,
    2023,
    2024,
    2025
  ],
  "by_year": {
    "2010": {
      "English": 17,
      "Chinese": 9,
      "Other": 5,
      "Vietnamese": 2,
      "Indian": 5,
      "French": 5,
      "Korean": 1,
      "German": 1,
      "Italian": 1,
      "Turkish": 1,
      "Spanish": 1,
      "Dutch": 1
    },
    "2011": {
      "Italian": 2,
      "Chinese": 10,
      "Indian": 4,
      "Persian": 2,
      "English": 19,
      "Other": 3,
      "Vietnamese": 3,
      "Korean": 4,
      "Spanish": 2,
      "Portuguese": 1
    },
    "2012": {
      "Chinese": 14,
      "German": 6,
      "Indian": 6,
      "Turkish": 1,
      "Other": 7,
      "English": 16,
      "Korean": 5,
      "Persian": 3,
      "French": 1,
      "Dutch": 1,
      "Italian": 1
    },
    "2013": {
      "Chinese": 18,
      "English": 25,
      "Italian": 1,
      "Spanish": 4,
      "Korean": 3,
      "Dutch": 2,
      "Indian": 2,
      "German": 2,
      "Other": 2
    },
    "2014": {
      "English": 22,
      "Chinese": 21,
      "Russian": 1,
      "Indian": 2,
      "Korean": 5,
      "Vietnamese": 1,
      "Italian": 2,
      "Other": 7,
      "German": 2,
      "Spanish": 1,
      "French": 3,
      "Portuguese": 1
    },
    "2015": {
      "Portuguese": 1,
      "Chinese": 19,
      "Indian": 4,
      "French": 6,
      "English": 13,
      "Spanish": 4,
      "Other": 4,
      "Italian": 1,
      "Turkish": 1,
      "Korean": 2,
      "Persian": 1
    },
    "2016": {
      "English": 20,
      "French": 2,
      "Chinese": 18,
      "German": 2,
      "Italian": 3,
      "Russian": 1,
      "Other": 3,
      "Vietnamese": 1,
      "Persian": 1,
      "Spanish": 2,
      "Dutch": 1
    },
    "2017": {
      "Korean": 4,
      "English": 20,
      "Turkish": 1,
      "Chinese": 24,
      "Vietnamese": 2,
      "Other": 4,
      "Portuguese": 1,
      "Indian": 3,
      "German": 2,
      "Italian": 3,
      "Russian": 1,
      "French": 4,
      "Dutch": 1
    },
    "2018": {
      "Chinese": 24,
      "French": 4,
      "English": 20,
      "Russian": 1,
      "Other": 2,
      "Indian": 6,
      "German": 3,
      "Spanish": 1,
      "Vietnamese": 1,
      "Italian": 1,
      "Portuguese": 1,
      "Korean": 1
    },
    "2019": {
      "English": 22,
      "Chinese": 24,
      "Other": 6,
      "Korean": 1,
      "French": 3,
      "Spanish": 2,
      "Vietnamese": 1,
      "German": 5,
      "Dutch": 2,
      "Indian": 3,
      "Italian": 1
    },
    "2020": {
      "Italian": 1,
      "Other": 8,
      "German": 2,
      "English": 23,
      "Chinese": 21,
      "Indian": 3,
      "Korean": 1,
      "Spanish": 4,
      "French": 3,
      "Dutch": 2
    },
    "2021": {
      "Chinese": 27,
      "German": 5,
      "English": 25,
      "French": 2,
      "Spanish": 1,
      "Other": 5,
      "Indian": 3,
      "Russian": 2,
      "Dutch": 3,
      "Korean": 2,
      "Italian": 1
    },
    "2022": {
      "Portuguese": 1,
      "Spanish": 1,
      "Chinese": 26,
      "English": 23,
      "Italian": 1,
      "Indian": 3,
      "Korean": 3,
      "German": 1,
      "Other": 4
    },
    "2023": {
      "Italian": 2,
      "English": 27,
      "Chinese": 28,
      "German": 7,
      "Other": 4,
      "Indian": 4,
      "Dutch": 3,
      "Persian": 1,
      "Russian": 2,
      "Korean": 1
    },
    "2024": {
      "Other": 5,
      "Persian": 3,
      "Indian": 2,
      "English": 19,
      "German": 2,
      "Chinese": 17,
      "Italian": 1,
      "French": 2,
      "Dutch": 1,
      "Korean": 1,
      "Spanish": 1,
      "Turkish": 1
    },
    "2025": {
      "Chinese": 30,
      "English": 14,
      "French": 2,
      "Indian": 4,
      "Korean": 6,
      "German": 1,
      "Other": 5,
      "Italian": 1,
      "Vietnamese": 1,
      "Spanish": 1,
      "Persian": 2,
      "Russian": 1,
      "Japanese": 1
    }
  },
  "total": {
    "English": 325,
    "Chinese": 330,
    "Other": 74,
    "Vietnamese": 12,
    "Indian": 54,
    "French": 37,
    "Korean": 40,
    "German": 41,
    "Italian": 23,
    "Turkish": 5,
    "Spanish": 25,
    "Dutch": 17,
    "Persian": 13,
    "Portuguese": 6,
    "Russian": 9,
    "Japanese": 1
  },
  "venues": {
    "2025": {
      "city": "Stony Brook",
      "country": "USA"
    },
    "2024": {
      "city": "Venice",
      "country": "Italy"
    },
    "2023": {
      "city": "Orlanda",
      "country": "USA"
    },
    "2022": {
      "city": "Mumbai",
      "country": "India"
    },
    "2021": {
      "city": "Virtual",
      "country": null
    },
    "2020": {
      "city": "Boston",
      "country": "USA"
    },
    "2019": {
      "city": "Phoenix",
      "country": "USA"
    },
    "2018": {
      "city": "Irvine",
      "country": "USA"
    },
    "2017": {
      "city": "Urbana-Champaign",
      "country": "USA"
    },
    "2016": {
      "city": "Antibes Juan-Les-Pins",
      "country": "France"
    },
    "2015": {
      "city": "Portland",
      "country": "USA"
    },
    "2014": {
      "city": "Austin",
      "country": "USA"
    },
    "2013": {
      "city": "Pittsburgh",
      "country": "USA"
    },
    "2012": {
      "city": "London",
      "country": "UK"
    },
    "2011": {
      "city": "San Jose",
      "country": "USA"
    },
    "2010": {
      "city": "New York",
      "country": "USA"
    },
    "2009": {
      "city": "Seattle",
      "country": "USA"
    },
    "2008": {
      "city": "Annapolis",
      "country": "USA"
    },
    "2007": {
      "city": "San Diego",
      "country": "USA"
    },
    "2006": {
      "city": "Saint-Malo",
      "country": "France"
    },
    "2005": {
      "city": "Banff",
      "country": "Canada"
    },
    "2004": {
      "city": "New York",
      "country": "USA"
    },
    "2003": {
      "city": "San Diego",
      "country": "USA"
    },
    "2002": {
      "city": "Marina del Rey",
      "country": "USA"
    },
    "2001": {
      "city": "Cambridge",
      "country": "USA"
    },
    "2000": {
      "city": "Santa Clara",
      "country": "USA"
    }
  },
  "rank_history": {
    "2012": "B",
    "2015": "B",
    "2019": "B",
    "2022": "B",
    "2026": "B"
  },
  "accept_rates": [
    {
      "year": 2025,
      "submitted": 382,
      "accepted": 66
    },
    {
      "year": 2024,
      "submitted": 336,
      "accepted": 52
    },
    {
      "year": 2023,
      "submitted": 339,
      "accepted": 54
    },
    {
      "year": 2022,
      "submitted": 303,
      "accepted": 59
    },
    {
      "year": 2021,
      "submitted": 315,
      "accepted": 38
    },
    {
      "year": 2020,
      "submitted": 280,
      "accepted": 55
    },
    {
      "year": 2019,
      "submitted": 317,
      "accepted": 50
    },
    {
      "year": 2018,
      "submitted": 270,
      "accepted": 54
    },
    {
      "year": 2017,
      "submitted": 203,
      "accepted": 26
    },
    {
      "year": 2016,
      "submitted": 208,
      "accepted": 28
    },
    {
      "year": 2015,
      "submitted": 239,
      "accepted": 32
    },
    {
      "year": 2014,
      "submitted": 237,
      "accepted": 40
    },
    {
      "year": 2013,
      "submitted": 196,
      "accepted": 26
    },
    {
      "year": 2012,
      "submitted": 203,
      "accepted": 31
    },
    {
      "year": 2011,
      "submitted": 177,
      "accepted": 26
    },
    {
      "year": 2010,
      "submitted": 184,
      "accepted": 29
    },
    {
      "year": 2009,
      "submitted": 180,
      "accepted": 27
    },
    {
      "year": 2008,
      "submitted": 201,
      "accepted": 36
    },
    {
      "year": 2007,
      "submitted": 179,
      "accepted": 29
    },
    {
      "year": 2006,
      "submitted": 219,
      "accepted": 30
    },
    {
      "year": 2005,
      "submitted": 237,
      "accepted": 31
    },
    {
      "year": 2004,
      "submitted": 265,
      "accepted": 33
    },
    {
      "year": 2003,
      "submitted": 222,
      "accepted": 26
    },
    {
      "year": 2002,
      "submitted": 170,
      "accepted": 23
    },
    {
      "year": 2001,
      "submitted": 233,
      "accepted": 29
    },
    {
      "year": 2000,
      "submitted": 165,
      "accepted": 28
    },
    {
      "year": 1999,
      "submitted": 92,
      "accepted": 18
    },
    {
      "year": 1998,
      "submitted": 136,
      "accepted": 25
    },
    {
      "year": 1997,
      "submitted": 130,
      "accepted": 25
    },
    {
      "year": 1996,
      "submitted": 110,
      "accepted": 24
    },
    {
      "year": 1995,
      "submitted": 123,
      "accepted": 27
    },
    {
      "year": 1982,
      "submitted": 60,
      "accepted": 27
    }
  ]
}